template/__init__.py
template/version.py
pyconfrdemo-0.0.11.dist-info/LICENSE
pyconfrdemo-0.0.11.dist-info/METADATA
pyconfrdemo-0.0.11.dist-info/WHEEL
pyconfrdemo-0.0.11.dist-info/top_level.txt
pyconfrdemo-0.0.11.dist-info/RECORD
