Metadata-Version: 2.1
Name: pyconfrdemo
Version: 0.0.11
Summary: Demo package for PyConFR 2023 demo
License: GNU GENERAL PUBLIC LICENSE
Requires-Python: >=3.10
License-File: LICENSE
